{"name": "TreeSitter", "version": "1.7.0", "sublime_text": ">=4107", "platforms": ["*"], "python_version": "3.8", "url": "https://github.com/sublime-treesitter/TreeSitter", "issues": "https://github.com/sublime-treesitter/TreeSitter/issues", "author": ["kylebebak"], "description": "Sublime Text Tree-sitter configuration and abstraction layer", "labels": ["tree-sitter", "navigation", "selection", "symbols", "parsers"], "libraries": [], "install_time": 1721368760.5446262, "release_time": "2024-05-11 03:09:40"}